physiolabxr/PhysioLabXR.py
physiolabxr/__init__.py
physiolabxr/_media/__init__.py
physiolabxr/_media/deprecated_pngs/next.png
physiolabxr/_media/deprecated_pngs/pause.png
physiolabxr/_media/deprecated_pngs/play.png
physiolabxr/_media/deprecated_pngs/pre.png
physiolabxr/_media/deprecated_pngs/stop.png
physiolabxr/_media/gifs/__init__.py
physiolabxr/_media/gifs/load_48px.gif
physiolabxr/_media/gifs/load_square_200px.gif
physiolabxr/_media/gifs/load_square_200px.svg
physiolabxr/_media/gifs/load_square_48px.gif
physiolabxr/_media/icons/__init__.py
physiolabxr/_media/icons/add.svg
physiolabxr/_media/icons/collapse.svg
physiolabxr/_media/icons/copy.svg
physiolabxr/_media/icons/dock_window.svg
physiolabxr/_media/icons/expand.svg
physiolabxr/_media/icons/minus.svg
physiolabxr/_media/icons/options.svg
physiolabxr/_media/icons/pause.svg
physiolabxr/_media/icons/pop_window.svg
physiolabxr/_media/icons/remove.svg
physiolabxr/_media/icons/start.svg
physiolabxr/_media/icons/stop.svg
physiolabxr/_media/icons/stream_available.png
physiolabxr/_media/icons/stream_unavailable.png
physiolabxr/_media/icons/stream_viz_active.png
physiolabxr/_media/icons/streamwidget_stream_available.svg
physiolabxr/_media/icons/streamwidget_stream_unavailable.svg
physiolabxr/_media/icons/streamwidget_stream_viz_active.svg
physiolabxr/_media/icons/terminate.svg
physiolabxr/_media/logo/RenaLabAppDeprecated.png
physiolabxr/_media/logo/__init__.py
physiolabxr/_media/logo/app_logo.ico
physiolabxr/_media/logo/app_logo.png
physiolabxr/_media/logo/splash_screen.png
physiolabxr/_media/readme/AllPlottingFormat.png
physiolabxr/_media/readme/PhysioLabXR Overview.png
physiolabxr/_media/readme/__init__.py
physiolabxr/_media/readme/screenshot.png
physiolabxr/_presets/README
physiolabxr/_presets/__init__.py
physiolabxr/_presets/Deprecated/NIRSport2.json
physiolabxr/_presets/Deprecated/OpenBCICyton8.json
physiolabxr/_presets/Deprecated/TImmWave.json
physiolabxr/_presets/Deprecated/VarjoEyeData.json
physiolabxr-1.1.3.dist-info/LICENSE
physiolabxr-1.1.3.dist-info/METADATA
physiolabxr-1.1.3.dist-info/WHEEL
physiolabxr-1.1.3.dist-info/entry_points.txt
physiolabxr-1.1.3.dist-info/top_level.txt
physiolabxr-1.1.3.dist-info/RECORD
