Metadata-Version: 2.1
Name: physiolabxr
Version: 1.1.3
Summary: PhysioLabXR
Author-email: Ziheng 'Leo' Li <apocalyvec@gmail.com>, Haowen 'John' Wei <haowenweijohn@gmail.com>, Ziwen 'Josie' Xie <jerseyxie@hotmail.com>
Project-URL: Homepage, https://github.com/physiolabxr/physiolabxr
Project-URL: Bug Tracker, https://github.com/physiolabxr/physiolabxr/issues
Project-URL: Documentation, https://physiolabxrdocs.readthedocs.io/en/latest/
Classifier: Programming Language :: Python :: 3
Classifier: License :: OSI Approved :: BSD License
Classifier: Operating System :: OS Independent
License-File: LICENSE
Requires-Dist: brainflow
Requires-Dist: numpy ~=1.26.0
Requires-Dist: PyQt6
Requires-Dist: pyserial
Requires-Dist: pylsl
Requires-Dist: scikit-learn
Requires-Dist: scipy ~=1.11.0
Requires-Dist: pyqtgraph
Requires-Dist: pyxdf
Requires-Dist: pyscreeze
Requires-Dist: opencv-python
Requires-Dist: pyzmq
Requires-Dist: setuptools
Requires-Dist: psutil
Requires-Dist: pytest-qt
Requires-Dist: numba
Requires-Dist: PyOpenGL
Requires-Dist: PyOpenGL-accelerate
Requires-Dist: soundfile
